string_date_controller/__init__.py
string_date_controller/date_determinator.py
string_date_controller/date_extractor.py
string_date_controller/date_formatter.py
string_date_controller/date_generator.py
string_date_controller/date_shifter.py
string_date_controller/timeseries_dates_application/__init__.py
string_date_controller/timeseries_dates_application/consts.py
string_date_controller/timeseries_dates_application/historical_dates_collector.py
string_date_controller/timeseries_dates_application/monthly_dates_collector.py
string_date_controller/timeseries_dates_application/yearly_dates_collector.py
tests/__init__.py
tests/conftest.py
tests/test_yearly_dates.py
string_date_controller-0.3.1.dist-info/METADATA
string_date_controller-0.3.1.dist-info/WHEEL
string_date_controller-0.3.1.dist-info/top_level.txt
string_date_controller-0.3.1.dist-info/RECORD
