Metadata-Version: 2.4
Name: string_date_controller
Version: 0.3.1
Summary: A Python module for string date manipulation and formatting
Home-page: https://github.com/nailen1/string_date_controller.git
Author: June Young Park
Author-email: juneyoungpaak@gmail.com
Keywords: date time formatting manipulation utility
Classifier: Development Status :: 3 - Alpha
Classifier: Intended Audience :: Developers
Classifier: Topic :: Software Development :: Libraries :: Python Modules
Classifier: Topic :: Software Development :: Libraries
Classifier: Programming Language :: Python :: 3
Classifier: Programming Language :: Python :: 3.11
Classifier: License :: OSI Approved :: MIT License
Classifier: Operating System :: OS Independent
Requires-Python: >=3.11
Requires-Dist: shining_pebbles>=0.5.5
Dynamic: author
Dynamic: author-email
Dynamic: classifier
Dynamic: description
Dynamic: description-content-type
Dynamic: home-page
Dynamic: keywords
Dynamic: requires-dist
Dynamic: requires-python
Dynamic: summary
